DMT/Hdev/__init__.py
DMT/Hdev/dut_hdev.py
DMT/config/DMT_config.yaml
DMT/config/__init__.py
DMT/core/__init__.py
DMT/core/circuit.py
DMT/core/constants.py
DMT/core/data_frame.py
DMT/core/data_processor.py
DMT/core/data_reader.py
DMT/core/database_manager.py
DMT/core/df_to_sweep.py
DMT/core/dmt_units.txt
DMT/core/docu_dut_lib.py
DMT/core/dut_circuit.py
DMT/core/dut_dummy.py
DMT/core/dut_lib.py
DMT/core/dut_meas.py
DMT/core/dut_tcad.py
DMT/core/dut_type.py
DMT/core/dut_view.py
DMT/core/hasher.py
DMT/core/mc_parameter.py
DMT/core/mc_skywater.py
DMT/core/mcard.py
DMT/core/naming.py
DMT/core/plot.py
DMT/core/plot_2yaxis.py
DMT/core/plot_smith.py
DMT/core/sim_con.py
DMT/core/singleton.py
DMT/core/sweep.py
DMT/core/sweep_def.py
DMT/core/technology.py
DMT/core/utils.py
DMT/core/va_file.py
DMT/exceptions/__init__.py
DMT/external/__init__.py
DMT/external/latex.py
DMT/external/os.py
DMT/external/pylatex.py
DMT/external/pypi.py
DMT/external/verilogae.py
DMT/libautodoc_template/bib.bib
DMT/libautodoc_template/documentation.tex
DMT/libautodoc_template/base/acronyms.tex
DMT/libautodoc_template/base/header.tex
DMT/libautodoc_template/content/conclusion.tex
DMT/libautodoc_template/content/deckblatt.tex
DMT/libautodoc_template/content/introduction.tex
DMT/ngspice/__init__.py
DMT/ngspice/dut_ngspice.py
DMT/xyce/__init__.py
DMT/xyce/dut_xyce.py
DMT_core-2.1.0.dist-info/LICENSE
DMT_core-2.1.0.dist-info/METADATA
DMT_core-2.1.0.dist-info/WHEEL
DMT_core-2.1.0.dist-info/top_level.txt
DMT_core-2.1.0.dist-info/RECORD
