Metadata-Version: 2.1
Name: DMT-core
Version: 2.1.0
Summary: Device Modeling Toolkit Core
Home-page: https://gitlab.com/dmt-development/dmt
Author: M.Mueller, M.Krattenmacher
Author-email: markus.mueller@semimod.de, mario.krattenmacher@semimod.de
License: GNU GPLv3+
Project-URL: Bug Tracker, https://gitlab.com/dmt-development/dmt
Project-URL: Documentation, https://dmt-development.gitlab.io/dmt-core/
Project-URL: Source Code, https://gitlab.com/dmt-development/dmt
Platform: UNKNOWN
Classifier: License :: OSI Approved :: GNU Affero General Public License v3
Classifier: Programming Language :: Python :: 3.8
Classifier: Programming Language :: Python :: 3.9
Classifier: Programming Language :: Python :: 3.10
Classifier: Programming Language :: Python :: 3.11
Classifier: Operating System :: OS Independent
Classifier: Topic :: Scientific/Engineering :: Electronic Design Automation (EDA)
License-File: LICENSE
Requires-Dist: colormath
Requires-Dist: cycler
Requires-Dist: h5py
Requires-Dist: joblib
Requires-Dist: more-itertools
Requires-Dist: numpy
Requires-Dist: pandas
Requires-Dist: pint
Requires-Dist: pyarrow
Requires-Dist: pytest
Requires-Dist: pyyaml
Requires-Dist: reprint
Requires-Dist: requests
Requires-Dist: scikit-rf
Requires-Dist: scipy
Requires-Dist: semver
Requires-Dist: verilogae (>=0.9b4)
Provides-Extra: hdf5
Requires-Dist: tables ; extra == 'hdf5'
Provides-Extra: develop
Requires-Dist: black ; extra == 'develop'
Requires-Dist: pylint ; extra == 'develop'
Provides-Extra: full
Requires-Dist: PySide2 ; extra == 'full'
Requires-Dist: PySide6 ; extra == 'full'
Requires-Dist: black ; extra == 'full'
Requires-Dist: matplotlib ; extra == 'full'
Requires-Dist: paramiko ; extra == 'full'
Requires-Dist: pylatex ; extra == 'full'
Requires-Dist: pylatexenc ; extra == 'full'
Requires-Dist: pylint ; extra == 'full'
Requires-Dist: pyqtgraph ; extra == 'full'
Requires-Dist: pysmithplot-3.10 ; extra == 'full'
Requires-Dist: scp ; extra == 'full'
Requires-Dist: tables ; extra == 'full'
Provides-Extra: latex
Requires-Dist: pylatex ; extra == 'latex'
Requires-Dist: pylatexenc ; extra == 'latex'
Provides-Extra: matplotlib
Requires-Dist: matplotlib ; extra == 'matplotlib'
Provides-Extra: pyqt5
Requires-Dist: PyQt5 ; extra == 'pyqt5'
Provides-Extra: pyqtgraph
Requires-Dist: pyqtgraph ; extra == 'pyqtgraph'
Provides-Extra: pyside2
Requires-Dist: PySide2 ; extra == 'pyside2'
Provides-Extra: pyside6
Requires-Dist: PySide6 ; extra == 'pyside6'
Provides-Extra: remote
Requires-Dist: paramiko ; extra == 'remote'
Requires-Dist: scp ; extra == 'remote'
Provides-Extra: smithplot
Requires-Dist: matplotlib ; extra == 'smithplot'
Requires-Dist: pysmithplot-3.10 ; extra == 'smithplot'
